{
  "version": "4.5.9",
  "flags": {},
  "shapes": [
    {
      "label": "Net",
      "points": [
        [
          280,
          0
        ],
        [
          640,
          171
        ]
      ],
      "origin": "fishing",
      "group_id": null,
      "shape_type": "rectangle",
      "flags": {}
    },
    {
      "label": "Rope",
      "points": [
        [
          435,
          408
        ],
        [
          538,
          543
        ]
      ],
      "origin": "fishing",
      "group_id": null,
      "shape_type": "rectangle",
      "flags": {}
    },
    {
      "label": "Rope",
      "points": [
        [
          252,
          0
        ],
        [
          698,
          186
        ]
      ],
      "origin": "fishing",
      "group_id": null,
      "shape_type": "rectangle",
      "flags": {}
    },
    {
      "label": "Plastic_Buoy",
      "points": [
        [
          533,
          113
        ],
        [
          694,
          266
        ]
      ],
      "origin": "fishing",
      "group_id": null,
      "shape_type": "rectangle",
      "flags": {}
    }
  ],
  "imagePath": "FD_1592.jpg",
  "imageData": null,
  "imageHeight": 800,
  "imageWidth": 1200,
  "date": "2021-10-21",
  "time": "11:50:20",
  "device": "Mavic2Pro",
  "camera": "L1D-20c",
  "shutter": 0.0125,
  "altitude": 5.0,
  "lat": null,
  "lon": null,
  "gtype": "Blue"
}