{
  "version": "4.5.9",
  "flags": {},
  "shapes": [
    {
      "label": "PET_Bottle",
      "points": [
        [
          785,
          1
        ],
        [
          878,
          45
        ]
      ],
      "origin": "coast",
      "group_id": null,
      "shape_type": "rectangle",
      "flags": {}
    },
    {
      "label": "PET_Bottle",
      "points": [
        [
          1048,
          125
        ],
        [
          1108,
          212
        ]
      ],
      "origin": "coast",
      "group_id": null,
      "shape_type": "rectangle",
      "flags": {}
    },
    {
      "label": "PET_Bottle",
      "points": [
        [
          616,
          150
        ],
        [
          655,
          208
        ]
      ],
      "origin": "coast",
      "group_id": null,
      "shape_type": "rectangle",
      "flags": {}
    },
    {
      "label": "Metal",
      "points": [
        [
          966,
          720
        ],
        [
          1027,
          754
        ]
      ],
      "origin": "coast",
      "group_id": null,
      "shape_type": "rectangle",
      "flags": {}
    }
  ],
  "imagePath": "FD_1722.jpg",
  "imageData": null,
  "imageHeight": 800,
  "imageWidth": 1200,
  "date": "2021-10-15",
  "time": "10:12:49",
  "device": "Phantom4Pro",
  "camera": "FC6310S",
  "shutter": 0.004166,
  "altitude": 10.0,
  "lat": null,
  "lon": null,
  "gtype": "Blue"
}