{
  "version": "4.5.9",
  "flags": {},
  "shapes": [
    {
      "label": "Metal",
      "points": [
        [
          305,
          431
        ],
        [
          411,
          537
        ]
      ],
      "origin": "coast",
      "group_id": null,
      "shape_type": "rectangle",
      "flags": {}
    },
    {
      "label": "Plastic_ETC",
      "points": [
        [
          1147,
          573
        ],
        [
          1200,
          625
        ]
      ],
      "origin": "coast",
      "group_id": null,
      "shape_type": "rectangle",
      "flags": {}
    },
    {
      "label": "Styrofoam_Piece",
      "points": [
        [
          966,
          249
        ],
        [
          1094,
          346
        ]
      ],
      "origin": "coast",
      "group_id": null,
      "shape_type": "rectangle",
      "flags": {}
    }
  ],
  "imagePath": "FD_236.jpg",
  "imageData": null,
  "imageHeight": 800,
  "imageWidth": 1200,
  "date": "2021-10-15",
  "time": "10:30:19",
  "device": "Phantom4Pro",
  "camera": "FC6310S",
  "shutter": 0.005,
  "altitude": 5.0,
  "lat": null,
  "lon": null,
  "gtype": "Blue"
}