{
  "version": "4.5.9",
  "flags": {},
  "shapes": [
    {
      "label": "PET_Bottle",
      "points": [
        [
          209,
          447
        ],
        [
          420,
          615
        ]
      ],
      "origin": "coast",
      "group_id": null,
      "shape_type": "rectangle",
      "flags": {}
    },
    {
      "label": "PET_Bottle",
      "points": [
        [
          413,
          483
        ],
        [
          482,
          550
        ]
      ],
      "origin": "coast",
      "group_id": null,
      "shape_type": "rectangle",
      "flags": {}
    },
    {
      "label": "PET_Bottle",
      "points": [
        [
          396,
          416
        ],
        [
          463,
          487
        ]
      ],
      "origin": "coast",
      "group_id": null,
      "shape_type": "rectangle",
      "flags": {}
    },
    {
      "label": "Styrofoam_Buoy",
      "points": [
        [
          1001,
          570
        ],
        [
          1200,
          800
        ]
      ],
      "origin": "aquafarm",
      "group_id": null,
      "shape_type": "rectangle",
      "flags": {}
    }
  ],
  "imagePath": "FD_497.jpg",
  "imageData": null,
  "imageHeight": 800,
  "imageWidth": 1200,
  "date": "2021-10-15",
  "time": "11:27:57",
  "device": "Phantom4Pro",
  "camera": "FC6310S",
  "shutter": 0.003125,
  "altitude": 5.0,
  "lat": null,
  "lon": null,
  "gtype": "Blue"
}