{
  "version": "4.5.9",
  "flags": {},
  "shapes": [
    {
      "label": "PET_Bottle",
      "points": [
        [
          356,
          214
        ],
        [
          417,
          253
        ]
      ],
      "origin": "coast",
      "group_id": null,
      "shape_type": "rectangle",
      "flags": {}
    },
    {
      "label": "PET_Bottle",
      "points": [
        [
          751,
          122
        ],
        [
          786,
          189
        ]
      ],
      "origin": "coast",
      "group_id": null,
      "shape_type": "rectangle",
      "flags": {}
    },
    {
      "label": "Glass",
      "points": [
        [
          778,
          513
        ],
        [
          843,
          548
        ]
      ],
      "origin": "coast",
      "group_id": null,
      "shape_type": "rectangle",
      "flags": {}
    },
    {
      "label": "Glass",
      "points": [
        [
          818,
          624
        ],
        [
          893,
          657
        ]
      ],
      "origin": "coast",
      "group_id": null,
      "shape_type": "rectangle",
      "flags": {}
    }
  ],
  "imagePath": "FD_529.jpg",
  "imageData": null,
  "imageHeight": 800,
  "imageWidth": 1200,
  "date": "2021-10-15",
  "time": "10:08:14",
  "device": "Phantom4Pro",
  "camera": "FC6310S",
  "shutter": 0.004166,
  "altitude": 10.0,
  "lat": null,
  "lon": null,
  "gtype": "Blue"
}