{
  "version": "4.5.9",
  "flags": {},
  "shapes": [
    {
      "label": "Rope",
      "points": [
        [
          1156,
          687
        ],
        [
          1186,
          759
        ]
      ],
      "origin": "fishing",
      "group_id": null,
      "shape_type": "rectangle",
      "flags": {}
    },
    {
      "label": "Rope",
      "points": [
        [
          536,
          170
        ],
        [
          585,
          193
        ]
      ],
      "origin": "fishing",
      "group_id": null,
      "shape_type": "rectangle",
      "flags": {}
    },
    {
      "label": "Glass",
      "points": [
        [
          1047,
          668
        ],
        [
          1071,
          763
        ]
      ],
      "origin": "coast",
      "group_id": null,
      "shape_type": "rectangle",
      "flags": {}
    },
    {
      "label": "Glass",
      "points": [
        [
          1070,
          696
        ],
        [
          1153,
          745
        ]
      ],
      "origin": "coast",
      "group_id": null,
      "shape_type": "rectangle",
      "flags": {}
    },
    {
      "label": "Glass",
      "points": [
        [
          1137,
          511
        ],
        [
          1200,
          543
        ]
      ],
      "origin": "coast",
      "group_id": null,
      "shape_type": "rectangle",
      "flags": {}
    },
    {
      "label": "Glass",
      "points": [
        [
          567,
          362
        ],
        [
          675,
          398
        ]
      ],
      "origin": "coast",
      "group_id": null,
      "shape_type": "rectangle",
      "flags": {}
    },
    {
      "label": "Metal",
      "points": [
        [
          892,
          688
        ],
        [
          943,
          755
        ]
      ],
      "origin": "coast",
      "group_id": null,
      "shape_type": "rectangle",
      "flags": {}
    },
    {
      "label": "Styrofoam_Piece",
      "points": [
        [
          953,
          691
        ],
        [
          1050,
          800
        ]
      ],
      "origin": "coast",
      "group_id": null,
      "shape_type": "rectangle",
      "flags": {}
    },
    {
      "label": "Plastic_Buoy",
      "points": [
        [
          576,
          141
        ],
        [
          635,
          192
        ]
      ],
      "origin": "fishing",
      "group_id": null,
      "shape_type": "rectangle",
      "flags": {}
    },
    {
      "label": "Metal",
      "points": [
        [
          1,
          80
        ],
        [
          60,
          133
        ]
      ],
      "origin": "coast",
      "group_id": null,
      "shape_type": "rectangle",
      "flags": {}
    },
    {
      "label": "Plastic_ETC",
      "points": [
        [
          1099,
          737
        ],
        [
          1177,
          790
        ]
      ],
      "origin": "fishing",
      "group_id": null,
      "shape_type": "rectangle",
      "flags": {}
    },
    {
      "label": "Net",
      "points": [
        [
          1045,
          514
        ],
        [
          1164,
          693
        ]
      ],
      "origin": "fishing",
      "group_id": null,
      "shape_type": "rectangle",
      "flags": {}
    }
  ],
  "imagePath": "FD_581.jpg",
  "imageData": null,
  "imageHeight": 800,
  "imageWidth": 1200,
  "date": "2021-10-14",
  "time": "13:49:10",
  "device": "Mavic2Pro",
  "camera": "L1D-20c",
  "shutter": 0.008333333333333333,
  "altitude": 10.0,
  "lat": null,
  "lon": null,
  "gtype": "Blue"
}