{
  "version": "4.5.9",
  "flags": {},
  "shapes": [
    {
      "label": "Styrofoam_Buoy",
      "points": [
        [
          466,
          396
        ],
        [
          924,
          799
        ]
      ],
      "origin": "aquafarm",
      "group_id": null,
      "shape_type": "rectangle",
      "flags": {}
    },
    {
      "label": "PET_Bottle",
      "points": [
        [
          56,
          526
        ],
        [
          245,
          594
        ]
      ],
      "origin": "coast",
      "group_id": null,
      "shape_type": "rectangle",
      "flags": {}
    },
    {
      "label": "Rope",
      "points": [
        [
          231,
          243
        ],
        [
          640,
          615
        ]
      ],
      "origin": "fishing",
      "group_id": null,
      "shape_type": "rectangle",
      "flags": {}
    },
    {
      "label": "Styrofoam_Piece",
      "points": [
        [
          917,
          73
        ],
        [
          1200,
          387
        ]
      ],
      "origin": "aquafarm",
      "group_id": null,
      "shape_type": "rectangle",
      "flags": {}
    },
    {
      "label": "Styrofoam_Box",
      "points": [
        [
          698,
          193
        ],
        [
          993,
          508
        ]
      ],
      "origin": "coast",
      "group_id": null,
      "shape_type": "rectangle",
      "flags": {}
    }
  ],
  "imagePath": "FD_8.jpg",
  "imageData": null,
  "imageHeight": 800,
  "imageWidth": 1200,
  "date": "2021-10-14",
  "time": "16:09:22",
  "device": "Phantom4Pro",
  "camera": "FC6310S",
  "shutter": 0.00625,
  "altitude": 5.0,
  "lat": null,
  "lon": null,
  "gtype": "Blue"
}