{
  "version": "4.5.9",
  "flags": {},
  "shapes": [
    {
      "label": "PET_Bottle",
      "points": [
        [
          248,
          691
        ],
        [
          427,
          759
        ]
      ],
      "origin": "coast",
      "group_id": null,
      "shape_type": "rectangle",
      "flags": {}
    },
    {
      "label": "PET_Bottle",
      "points": [
        [
          842,
          555
        ],
        [
          1058,
          652
        ]
      ],
      "origin": "coast",
      "group_id": null,
      "shape_type": "rectangle",
      "flags": {}
    },
    {
      "label": "Plastic_ETC",
      "points": [
        [
          983,
          689
        ],
        [
          1063,
          800
        ]
      ],
      "origin": "fishing",
      "group_id": null,
      "shape_type": "rectangle",
      "flags": {}
    },
    {
      "label": "Rope",
      "points": [
        [
          1056,
          209
        ],
        [
          1200,
          270
        ]
      ],
      "origin": "fishing",
      "group_id": null,
      "shape_type": "rectangle",
      "flags": {}
    },
    {
      "label": "PET_Bottle",
      "points": [
        [
          1097,
          1
        ],
        [
          1174,
          46
        ]
      ],
      "origin": "coast",
      "group_id": null,
      "shape_type": "rectangle",
      "flags": {}
    }
  ],
  "imagePath": "FD_826.jpg",
  "imageData": null,
  "imageHeight": 800,
  "imageWidth": 1200,
  "date": "2021-10-13",
  "time": "15:39:23",
  "device": "Mavic2Pro",
  "camera": "L1D-20c",
  "shutter": 0.0125,
  "altitude": 5.0,
  "lat": null,
  "lon": null,
  "gtype": "Blue"
}