{
  "version": "4.5.9",
  "flags": {},
  "shapes": [
    {
      "label": "PET_Bottle",
      "points": [
        [
          35,
          430
        ],
        [
          141,
          562
        ]
      ],
      "origin": "coast",
      "group_id": null,
      "shape_type": "rectangle",
      "flags": {}
    },
    {
      "label": "Plastic_Buoy",
      "points": [
        [
          196,
          268
        ],
        [
          253,
          335
        ]
      ],
      "origin": "fishing",
      "group_id": null,
      "shape_type": "rectangle",
      "flags": {}
    },
    {
      "label": "Plastic_Buoy",
      "points": [
        [
          110,
          624
        ],
        [
          167,
          686
        ]
      ],
      "origin": "fishing",
      "group_id": null,
      "shape_type": "rectangle",
      "flags": {}
    },
    {
      "label": "Plastic_Buoy",
      "points": [
        [
          85,
          680
        ],
        [
          125,
          743
        ]
      ],
      "origin": "fishing",
      "group_id": null,
      "shape_type": "rectangle",
      "flags": {}
    },
    {
      "label": "Plastic_Buoy",
      "points": [
        [
          167,
          738
        ],
        [
          236,
          788
        ]
      ],
      "origin": "fishing",
      "group_id": null,
      "shape_type": "rectangle",
      "flags": {}
    },
    {
      "label": "Rope",
      "points": [
        [
          90,
          743
        ],
        [
          174,
          791
        ]
      ],
      "origin": "fishing",
      "group_id": null,
      "shape_type": "rectangle",
      "flags": {}
    },
    {
      "label": "Plastic_Buoy",
      "points": [
        [
          698,
          337
        ],
        [
          760,
          402
        ]
      ],
      "origin": "fishing",
      "group_id": null,
      "shape_type": "rectangle",
      "flags": {}
    },
    {
      "label": "Plastic_Buoy",
      "points": [
        [
          723,
          368
        ],
        [
          791,
          431
        ]
      ],
      "origin": "fishing",
      "group_id": null,
      "shape_type": "rectangle",
      "flags": {}
    },
    {
      "label": "Metal",
      "points": [
        [
          1073,
          9
        ],
        [
          1130,
          60
        ]
      ],
      "origin": "coast",
      "group_id": null,
      "shape_type": "rectangle",
      "flags": {}
    },
    {
      "label": "Metal",
      "points": [
        [
          1023,
          67
        ],
        [
          1078,
          127
        ]
      ],
      "origin": "coast",
      "group_id": null,
      "shape_type": "rectangle",
      "flags": {}
    },
    {
      "label": "Rope",
      "points": [
        [
          154,
          552
        ],
        [
          245,
          637
        ]
      ],
      "origin": "fishing",
      "group_id": null,
      "shape_type": "rectangle",
      "flags": {}
    },
    {
      "label": "Rope",
      "points": [
        [
          219,
          699
        ],
        [
          271,
          759
        ]
      ],
      "origin": "fishing",
      "group_id": null,
      "shape_type": "rectangle",
      "flags": {}
    }
  ],
  "imagePath": "FD_906.jpg",
  "imageData": null,
  "imageHeight": 800,
  "imageWidth": 1200,
  "date": "2021-10-21",
  "time": "15:02:28",
  "device": "Mavic2Pro",
  "camera": "L1D-20c",
  "shutter": 0.00625,
  "altitude": 5.0,
  "lat": null,
  "lon": null,
  "gtype": "Blue"
}