{
  "version": "4.5.9",
  "flags": {},
  "shapes": [
    {
      "label": "Plastic_Buoy",
      "points": [
        [
          433,
          1
        ],
        [
          736,
          248
        ]
      ],
      "origin": "fishing",
      "group_id": null,
      "shape_type": "rectangle",
      "flags": {}
    },
    {
      "label": "Rope",
      "points": [
        [
          284,
          189
        ],
        [
          415,
          413
        ]
      ],
      "origin": "fishing",
      "group_id": null,
      "shape_type": "rectangle",
      "flags": {}
    },
    {
      "label": "Net",
      "points": [
        [
          1,
          230
        ],
        [
          543,
          800
        ]
      ],
      "origin": "fishing",
      "group_id": null,
      "shape_type": "rectangle",
      "flags": {}
    },
    {
      "label": "Rope",
      "points": [
        [
          430,
          126
        ],
        [
          577,
          249
        ]
      ],
      "origin": "fishing",
      "group_id": null,
      "shape_type": "rectangle",
      "flags": {}
    }
  ],
  "imagePath": "FD_1682.jpg",
  "imageData": null,
  "imageHeight": 800,
  "imageWidth": 1200,
  "date": "2021-10-21",
  "time": "14:43:31",
  "device": "Mavic2Pro",
  "camera": "L1D-20c",
  "shutter": 0.004166666666666667,
  "altitude": 5.0,
  "lat": null,
  "lon": null,
  "gtype": "Blue"
}