{
  "version": "4.5.9",
  "flags": {},
  "shapes": [
    {
      "label": "PET_Bottle",
      "points": [
        [
          701,
          748
        ],
        [
          793,
          800
        ]
      ],
      "origin": "coast",
      "group_id": null,
      "shape_type": "rectangle",
      "flags": {}
    },
    {
      "label": "PET_Bottle",
      "points": [
        [
          30,
          603
        ],
        [
          126,
          759
        ]
      ],
      "origin": "coast",
      "group_id": null,
      "shape_type": "rectangle",
      "flags": {}
    },
    {
      "label": "PET_Bottle",
      "points": [
        [
          917,
          87
        ],
        [
          985,
          243
        ]
      ],
      "origin": "coast",
      "group_id": null,
      "shape_type": "rectangle",
      "flags": {}
    }
  ],
  "imagePath": "FD_27.jpg",
  "imageData": null,
  "imageHeight": 800,
  "imageWidth": 1200,
  "date": "2021-10-14",
  "time": "09:51:13",
  "device": "Phantom4Pro",
  "camera": "FC6310S",
  "shutter": 0.00625,
  "altitude": 5.0,
  "lat": null,
  "lon": null,
  "gtype": "Blue"
}