{
  "version": "4.5.9",
  "flags": {},
  "shapes": [
    {
      "label": "Plastic_Buoy",
      "points": [
        [
          27,
          13
        ],
        [
          67,
          96
        ]
      ],
      "origin": "fishing",
      "group_id": null,
      "shape_type": "rectangle",
      "flags": {}
    },
    {
      "label": "Plastic_Buoy",
      "points": [
        [
          80,
          1
        ],
        [
          136,
          29
        ]
      ],
      "origin": "fishing",
      "group_id": null,
      "shape_type": "rectangle",
      "flags": {}
    },
    {
      "label": "Plastic_Buoy",
      "points": [
        [
          128,
          1
        ],
        [
          290,
          138
        ]
      ],
      "origin": "fishing",
      "group_id": null,
      "shape_type": "rectangle",
      "flags": {}
    },
    {
      "label": "Plastic_Buoy",
      "points": [
        [
          280,
          64
        ],
        [
          326,
          92
        ]
      ],
      "origin": "fishing",
      "group_id": null,
      "shape_type": "rectangle",
      "flags": {}
    },
    {
      "label": "Plastic_Buoy",
      "points": [
        [
          323,
          22
        ],
        [
          397,
          127
        ]
      ],
      "origin": "fishing",
      "group_id": null,
      "shape_type": "rectangle",
      "flags": {}
    },
    {
      "label": "Plastic_Buoy",
      "points": [
        [
          385,
          53
        ],
        [
          434,
          134
        ]
      ],
      "origin": "fishing",
      "group_id": null,
      "shape_type": "rectangle",
      "flags": {}
    },
    {
      "label": "Plastic_Buoy",
      "points": [
        [
          532,
          1
        ],
        [
          594,
          20
        ]
      ],
      "origin": "fishing",
      "group_id": null,
      "shape_type": "rectangle",
      "flags": {}
    },
    {
      "label": "Rope",
      "points": [
        [
          35,
          1
        ],
        [
          453,
          240
        ]
      ],
      "origin": "fishing",
      "group_id": null,
      "shape_type": "rectangle",
      "flags": {}
    },
    {
      "label": "Net",
      "points": [
        [
          841,
          602
        ],
        [
          1200,
          800
        ]
      ],
      "origin": "fishing",
      "group_id": null,
      "shape_type": "rectangle",
      "flags": {}
    },
    {
      "label": "Rope",
      "points": [
        [
          477,
          1
        ],
        [
          591,
          56
        ]
      ],
      "origin": "fishing",
      "group_id": null,
      "shape_type": "rectangle",
      "flags": {}
    }
  ],
  "imagePath": "FD_326.jpg",
  "imageData": null,
  "imageHeight": 800,
  "imageWidth": 1200,
  "date": "2021-10-21",
  "time": "11:19:45",
  "device": "Mavic2Pro",
  "camera": "L1D-20c",
  "shutter": 0.005,
  "altitude": 5.0,
  "lat": null,
  "lon": null,
  "gtype": "Blue"
}