{
  "version": "4.5.9",
  "flags": {},
  "shapes": [
    {
      "label": "Rope",
      "points": [
        [
          1,
          338
        ],
        [
          255,
          495
        ]
      ],
      "origin": "fishing",
      "group_id": null,
      "shape_type": "rectangle",
      "flags": {}
    },
    {
      "label": "Plastic_Buoy",
      "points": [
        [
          1893,
          1986
        ],
        [
          2261,
          2215
        ]
      ],
      "origin": "fishing",
      "group_id": null,
      "shape_type": "rectangle",
      "flags": {}
    },
    {
      "label": "Rope",
      "points": [
        [
          937,
          1
        ],
        [
          2836,
          1140
        ]
      ],
      "origin": "fishing",
      "group_id": null,
      "shape_type": "rectangle",
      "flags": {}
    }
  ],
  "imagePath": "FD_775.jpg",
  "imageData": null,
  "imageHeight": 3456,
  "imageWidth": 3456,
  "date": "2021-10-22",
  "time": "11:09:00",
  "device": "GalaxyA8",
  "camera": "SM-A810S",
  "shutter": 0.0024752475247524753,
  "altitude": 0.0,
  "lat": null,
  "lon": null,
  "gtype": "Blue"
}