{
  "version": "4.5.9",
  "flags": {},
  "shapes": [
    {
      "label": "Glass",
      "points": [
        [
          31,
          356
        ],
        [
          132,
          424
        ]
      ],
      "origin": "coast",
      "group_id": null,
      "shape_type": "rectangle",
      "flags": {}
    },
    {
      "label": "Metal",
      "points": [
        [
          133,
          125
        ],
        [
          172,
          161
        ]
      ],
      "origin": "coast",
      "group_id": null,
      "shape_type": "rectangle",
      "flags": {}
    },
    {
      "label": "Styrofoam_Piece",
      "points": [
        [
          1,
          41
        ],
        [
          51,
          96
        ]
      ],
      "origin": "aquafarm",
      "group_id": null,
      "shape_type": "rectangle",
      "flags": {}
    }
  ],
  "imagePath": "FD_805.jpg",
  "imageData": null,
  "imageHeight": 800,
  "imageWidth": 1200,
  "date": "2021-10-13",
  "time": "15:22:27",
  "device": "Mavic2Pro",
  "camera": "L1D-20c",
  "shutter": 0.0125,
  "altitude": 5.0,
  "lat": null,
  "lon": null,
  "gtype": "Blue"
}